{
  "source": "youtube",
  "source_url": "https://www.youtube.com/watch?v=IoAFVE2EYR8",
  "video_id": "IoAFVE2EYR8",
  "scraped_at": "2026-02-09T18:45:34.901953",
  "dj_name": "donit",
  "mix_title": "Ultimate Rave Mix 2025",
  "duration_seconds": 5399,
  "date": "20250106",
  "description": "Like last year, here's a mix featuring various Rave music, including Peak Time Techno, Tech Trance, Progressive, Future Rave and Uplifting Trance! I hope you enjoy!\n\n0:00:00 Hardwell feat. Bright Lights - Shotgun (Intro Edit)\n0:01:50 MatricK & XavieR - Take Control\n0:02:45 ShortRound - I Wanna Rave\n0:04:29 Kevin Kitchen - Coe\n0:05:34 Taylor Torrence - Ignition\n0:07:01 Mark Sixma & Achilles & Justin J. Moore - Being Alone\n0:09:41 Toxic Joy - Lose Your Mind\n0:12:00 Starkillers - Discoteka (Griffo Edit)\n0:13:55 Matt Ice - Vibration\n0:17:09 Kazden & Kevin Krissen & Fly D - Control\n0:19:12 Hardwell & Will Sparks - Twisted\n0:20:59 Kide IT - Vibin'\n0:23:35 Retrika & Alex Mueller & Alvi - Release The Energy\n0:26:31 Steve Dekay - Drop\n0:29:39 Domeno feat. Chloe Doyon - Before It's Over\n0:31:02 Victor Ruiz - Touch The Darkness\n0:32:52 Delerium - Silence (Nick James & Rune Bootleg)\n0:35:44 Ozgun & Forehand - The Underground\n0:38:48 Kazden & Karasso - This Rave\n0:40:02 AKKI - Get Up\n0:42:40 FOVOS - Free\n0:45:11 Agus Zack & Maikko - Deep Inside\n0:46:55 Kohey & Sunge - Welcome To The Jungle\n0:49:40 Broken Frequency feat. MC Roga - Can You Hear Me\n0:52:09 MANTZA - Control\n0:54:57 Mark Sherry & Steve Dekay - Smiley\n0:59:53 Mark Michael - Transcendence\n1:05:18 Sam Willetts - Do My Thing\n1:09:02 FOVOS - For The Techno\n1:11:11 T78 x MOTVS - Crescendo\n1:16:38 Ronski Speed & Sygma - AZURE (Francesca Fagiani Remix)\n1:19:18 David Forbes x Davey Asprey - Lonach\n1:23:18 Becking - Just Be\n1:26:20 donit - Technology",
  "genres": [
    "techno mix",
    "rave mix",
    "rave mix 2025",
    "ultimate rave mix",
    "future rave mix",
    "future rave 2025",
    "donit",
    "donit silvester mix"
  ],
  "tracklist": [
    {
      "position": 1,
      "artist": "Hardwell feat. Bright Lights",
      "title": "Shotgun",
      "timestamp": "0:00:00",
      "timestamp_seconds": 0
    },
    {
      "position": 2,
      "artist": "MatricK & XavieR",
      "title": "Take Control",
      "timestamp": "0:01:50",
      "timestamp_seconds": 110
    },
    {
      "position": 3,
      "artist": "ShortRound",
      "title": "I Wanna Rave",
      "timestamp": "0:02:45",
      "timestamp_seconds": 165
    },
    {
      "position": 4,
      "artist": "Kevin Kitchen",
      "title": "Coe",
      "timestamp": "0:04:29",
      "timestamp_seconds": 269
    },
    {
      "position": 5,
      "artist": "Taylor Torrence",
      "title": "Ignition",
      "timestamp": "0:05:34",
      "timestamp_seconds": 334
    },
    {
      "position": 6,
      "artist": "Mark Sixma & Achilles & Justin J. Moore",
      "title": "Being Alone",
      "timestamp": "0:07:01",
      "timestamp_seconds": 421
    },
    {
      "position": 7,
      "artist": "Toxic Joy",
      "title": "Lose Your Mind",
      "timestamp": "0:09:41",
      "timestamp_seconds": 581
    },
    {
      "position": 8,
      "artist": "Starkillers",
      "title": "Discoteka",
      "timestamp": "0:12:00",
      "timestamp_seconds": 720
    },
    {
      "position": 9,
      "artist": "Matt Ice",
      "title": "Vibration",
      "timestamp": "0:13:55",
      "timestamp_seconds": 835
    },
    {
      "position": 10,
      "artist": "Kazden & Kevin Krissen & Fly D",
      "title": "Control",
      "timestamp": "0:17:09",
      "timestamp_seconds": 1029
    },
    {
      "position": 11,
      "artist": "Hardwell & Will Sparks",
      "title": "Twisted",
      "timestamp": "0:19:12",
      "timestamp_seconds": 1152
    },
    {
      "position": 12,
      "artist": "Kide IT",
      "title": "Vibin'",
      "timestamp": "0:20:59",
      "timestamp_seconds": 1259
    },
    {
      "position": 13,
      "artist": "Retrika & Alex Mueller & Alvi",
      "title": "Release The Energy",
      "timestamp": "0:23:35",
      "timestamp_seconds": 1415
    },
    {
      "position": 14,
      "artist": "Steve Dekay",
      "title": "Drop",
      "timestamp": "0:26:31",
      "timestamp_seconds": 1591
    },
    {
      "position": 15,
      "artist": "Domeno feat. Chloe Doyon",
      "title": "Before It's Over",
      "timestamp": "0:29:39",
      "timestamp_seconds": 1779
    },
    {
      "position": 16,
      "artist": "Victor Ruiz",
      "title": "Touch The Darkness",
      "timestamp": "0:31:02",
      "timestamp_seconds": 1862
    },
    {
      "position": 17,
      "artist": "Delerium",
      "title": "Silence",
      "timestamp": "0:32:52",
      "timestamp_seconds": 1972
    },
    {
      "position": 18,
      "artist": "Ozgun & Forehand",
      "title": "The Underground",
      "timestamp": "0:35:44",
      "timestamp_seconds": 2144
    },
    {
      "position": 19,
      "artist": "Kazden & Karasso",
      "title": "This Rave",
      "timestamp": "0:38:48",
      "timestamp_seconds": 2328
    },
    {
      "position": 20,
      "artist": "AKKI",
      "title": "Get Up",
      "timestamp": "0:40:02",
      "timestamp_seconds": 2402
    },
    {
      "position": 21,
      "artist": "FOVOS",
      "title": "Free",
      "timestamp": "0:42:40",
      "timestamp_seconds": 2560
    },
    {
      "position": 22,
      "artist": "Agus Zack & Maikko",
      "title": "Deep Inside",
      "timestamp": "0:45:11",
      "timestamp_seconds": 2711
    },
    {
      "position": 23,
      "artist": "Kohey & Sunge",
      "title": "Welcome To The Jungle",
      "timestamp": "0:46:55",
      "timestamp_seconds": 2815
    },
    {
      "position": 24,
      "artist": "Broken Frequency feat. MC Roga",
      "title": "Can You Hear Me",
      "timestamp": "0:49:40",
      "timestamp_seconds": 2980
    },
    {
      "position": 25,
      "artist": "MANTZA",
      "title": "Control",
      "timestamp": "0:52:09",
      "timestamp_seconds": 3129
    },
    {
      "position": 26,
      "artist": "Mark Sherry & Steve Dekay",
      "title": "Smiley",
      "timestamp": "0:54:57",
      "timestamp_seconds": 3297
    },
    {
      "position": 27,
      "artist": "Mark Michael",
      "title": "Transcendence",
      "timestamp": "0:59:53",
      "timestamp_seconds": 3593
    },
    {
      "position": 28,
      "artist": "Sam Willetts",
      "title": "Do My Thing",
      "timestamp": "1:05:18",
      "timestamp_seconds": 3918
    },
    {
      "position": 29,
      "artist": "FOVOS",
      "title": "For The Techno",
      "timestamp": "1:09:02",
      "timestamp_seconds": 4142
    },
    {
      "position": 30,
      "artist": "T78 x MOTVS",
      "title": "Crescendo",
      "timestamp": "1:11:11",
      "timestamp_seconds": 4271
    },
    {
      "position": 31,
      "artist": "Ronski Speed & Sygma",
      "title": "AZURE",
      "timestamp": "1:16:38",
      "timestamp_seconds": 4598
    },
    {
      "position": 32,
      "artist": "David Forbes x Davey Asprey",
      "title": "Lonach",
      "timestamp": "1:19:18",
      "timestamp_seconds": 4758
    },
    {
      "position": 33,
      "artist": "Becking",
      "title": "Just Be",
      "timestamp": "1:23:18",
      "timestamp_seconds": 4998
    },
    {
      "position": 34,
      "artist": "donit",
      "title": "Technology",
      "timestamp": "1:26:20",
      "timestamp_seconds": 5180
    }
  ],
  "audio_links": [
    "https://www.youtube.com/watch?v=IoAFVE2EYR8"
  ],
  "channel": "donit",
  "view_count": 254372,
  "mix_id": "donit_20250106_ultimateravemix2025_fe0176dd"
}