{
  "source": "youtube",
  "source_url": "https://www.youtube.com/watch?v=7WxYqlwIYqM",
  "video_id": "7WxYqlwIYqM",
  "scraped_at": "2026-02-09T18:45:23.341982",
  "dj_name": "Techno Mix",
  "mix_title": "TECHNO MIX 2025 \ud83e\udd29 Remixes Of Popular Songs \ud83d\ude0f Techno Bangers #018",
  "duration_seconds": 3766,
  "date": "20250222",
  "description": "\ud83d\udd25 TECHNO MIX 2024 \ud83e\udd18 | Remixes Of Popular Songs \ud83c\udfb6 | Techno Bangers\ud83c\udfa7\n\nGet ready to dive into an electrifying journey of beats, bass, and energy with TECHNO MIX 2024! \ud83d\ude80 This mix is packed with the hottest remixes of your favorite songs and pulsating techno bangers that will keep you grooving all night long. \ud83c\udf89\n\nTimestamp:\n00:00 Onur Ormen, NDR, TECHNO KING - Sweat (feat. KOANS)\n02:40 Yellow Pvnk, TECHNO KING, GopStop - Push Up\n04:46 TECHNO KING - Bloody Mary\n06:32 TECHNO KING - Sweater Weather\n08:23 Cour, Snoblack, TECHNO KING  - Winter (from The Four Seasons)\n10:22 TECHNO KING - Let Me Love You\n12:22 SENSE, TECHNO KING - Beggin'\n14:13 TECHNO KING - Moth To A Flame\n17:15 Yellow Pvnk, GopStop, TECHNO KING - DADDY DJ\n19:14 HITAK, TECHNO KING - Makeba\n21:27 Yellow Pvnk , Booty Leak , TECHNO KING - What Is Love\n23:07 Nyezo, Murphy - Bandages\n24:59 New Beat Order, HYPR, TECHNO KING feat. KIMERA V - Maniac\n27:28 TECHNO KING - Dancing With Your Ghost\n29:08 midnight berlin, 9Lives, TECHNO KING - We Found Love\n31:05 TECHNO KING - Moth To A Flame\n34:06 New Beat Order, HYPR, TECHNO KING - Radioactive\n36:22 New Beat Order, HYPR, TECHNO KING - Stereo Love\n38:47 New Beat Order, tekknological, TECHNO KING - Safe and Sound\n40:52 Yellow Pvnk, GopStop, TECHNO KING - Forever Young\n43:02 Dream Chaos, TECHNO KING feat. Nito-Onna - Stupid\n44:41 ATHYN, Garonzos & TECHNO KING - 10.35 (feat Nito-Onna)\n46:49 Ken, TECHNO KING - Infinity\n48:43 MetaBoy, DVO, TECHNO KING - I Adore You\n50:42 Olymixed, TECHNO KING - Eyes Don't Lie\n52:53 PUGO, Hugge, TECHNO KING - Upside Down (feat. EMMY)\n55:12 Sense, TECHNO KING - I Hate U, i Love U\n57:02 Yellow Pvnk , Booty Leak , TECHNO KING - What Is Love\n58:43 Yellow Pvnk, Saimon Music, TECHNO KING - Faded\n1:00:41 New Beat Order, HYPR, TECHNO KING - Payphone\n\nWhat\u2019s inside?\n\ud83c\udfb5 Mind-blowing remixes of popular tracks\n\ud83c\udfb5 High-energy techno beats to set the dance floor on fire\n\ud83c\udfb5 The ultimate vibe for parties, workouts, or just chilling\n\n\u2728 Perfect for:\n\u2714\ufe0f Rave enthusiast",
  "genres": [
    "techno mix",
    "remix techno mix",
    "best mix techno",
    "dark techno mix",
    "techno music mix",
    "techno live mix",
    "techno mix 2024",
    "techno remix",
    "techno",
    "hard techno"
  ],
  "tracklist": [
    {
      "position": 1,
      "artist": "Onur Ormen, NDR, TECHNO KING",
      "title": "Sweat",
      "timestamp": "00:00",
      "timestamp_seconds": 0
    },
    {
      "position": 2,
      "artist": "Yellow Pvnk, TECHNO KING, GopStop",
      "title": "Push Up",
      "timestamp": "02:40",
      "timestamp_seconds": 160
    },
    {
      "position": 3,
      "artist": "TECHNO KING",
      "title": "Bloody Mary",
      "timestamp": "04:46",
      "timestamp_seconds": 286
    },
    {
      "position": 4,
      "artist": "TECHNO KING",
      "title": "Sweater Weather",
      "timestamp": "06:32",
      "timestamp_seconds": 392
    },
    {
      "position": 5,
      "artist": "Cour, Snoblack, TECHNO KING",
      "title": "Winter",
      "timestamp": "08:23",
      "timestamp_seconds": 503
    },
    {
      "position": 6,
      "artist": "TECHNO KING",
      "title": "Let Me Love You",
      "timestamp": "10:22",
      "timestamp_seconds": 622
    },
    {
      "position": 7,
      "artist": "SENSE, TECHNO KING",
      "title": "Beggin'",
      "timestamp": "12:22",
      "timestamp_seconds": 742
    },
    {
      "position": 8,
      "artist": "TECHNO KING",
      "title": "Moth To A Flame",
      "timestamp": "14:13",
      "timestamp_seconds": 853
    },
    {
      "position": 9,
      "artist": "Yellow Pvnk, GopStop, TECHNO KING",
      "title": "DADDY DJ",
      "timestamp": "17:15",
      "timestamp_seconds": 1035
    },
    {
      "position": 10,
      "artist": "HITAK, TECHNO KING",
      "title": "Makeba",
      "timestamp": "19:14",
      "timestamp_seconds": 1154
    },
    {
      "position": 11,
      "artist": "Yellow Pvnk , Booty Leak , TECHNO KING",
      "title": "What Is Love",
      "timestamp": "21:27",
      "timestamp_seconds": 1287
    },
    {
      "position": 12,
      "artist": "Nyezo, Murphy",
      "title": "Bandages",
      "timestamp": "23:07",
      "timestamp_seconds": 1387
    },
    {
      "position": 13,
      "artist": "New Beat Order, HYPR, TECHNO KING feat. KIMERA V",
      "title": "Maniac",
      "timestamp": "24:59",
      "timestamp_seconds": 1499
    },
    {
      "position": 14,
      "artist": "TECHNO KING",
      "title": "Dancing With Your Ghost",
      "timestamp": "27:28",
      "timestamp_seconds": 1648
    },
    {
      "position": 15,
      "artist": "midnight berlin, 9Lives, TECHNO KING",
      "title": "We Found Love",
      "timestamp": "29:08",
      "timestamp_seconds": 1748
    },
    {
      "position": 16,
      "artist": "TECHNO KING",
      "title": "Moth To A Flame",
      "timestamp": "31:05",
      "timestamp_seconds": 1865
    },
    {
      "position": 17,
      "artist": "New Beat Order, HYPR, TECHNO KING",
      "title": "Radioactive",
      "timestamp": "34:06",
      "timestamp_seconds": 2046
    },
    {
      "position": 18,
      "artist": "New Beat Order, HYPR, TECHNO KING",
      "title": "Stereo Love",
      "timestamp": "36:22",
      "timestamp_seconds": 2182
    },
    {
      "position": 19,
      "artist": "New Beat Order, tekknological, TECHNO KING",
      "title": "Safe and Sound",
      "timestamp": "38:47",
      "timestamp_seconds": 2327
    },
    {
      "position": 20,
      "artist": "Yellow Pvnk, GopStop, TECHNO KING",
      "title": "Forever Young",
      "timestamp": "40:52",
      "timestamp_seconds": 2452
    },
    {
      "position": 21,
      "artist": "Dream Chaos, TECHNO KING feat. Nito-Onna",
      "title": "Stupid",
      "timestamp": "43:02",
      "timestamp_seconds": 2582
    },
    {
      "position": 22,
      "artist": "ATHYN, Garonzos & TECHNO KING",
      "title": "10.35",
      "timestamp": "44:41",
      "timestamp_seconds": 2681
    },
    {
      "position": 23,
      "artist": "Ken, TECHNO KING",
      "title": "Infinity",
      "timestamp": "46:49",
      "timestamp_seconds": 2809
    },
    {
      "position": 24,
      "artist": "MetaBoy, DVO, TECHNO KING",
      "title": "I Adore You",
      "timestamp": "48:43",
      "timestamp_seconds": 2923
    },
    {
      "position": 25,
      "artist": "Olymixed, TECHNO KING",
      "title": "Eyes Don't Lie",
      "timestamp": "50:42",
      "timestamp_seconds": 3042
    },
    {
      "position": 26,
      "artist": "PUGO, Hugge, TECHNO KING",
      "title": "Upside Down",
      "timestamp": "52:53",
      "timestamp_seconds": 3173
    },
    {
      "position": 27,
      "artist": "Sense, TECHNO KING",
      "title": "I Hate U, i Love U",
      "timestamp": "55:12",
      "timestamp_seconds": 3312
    },
    {
      "position": 28,
      "artist": "Yellow Pvnk , Booty Leak , TECHNO KING",
      "title": "What Is Love",
      "timestamp": "57:02",
      "timestamp_seconds": 3422
    },
    {
      "position": 29,
      "artist": "Yellow Pvnk, Saimon Music, TECHNO KING",
      "title": "Faded",
      "timestamp": "58:43",
      "timestamp_seconds": 3523
    },
    {
      "position": 30,
      "artist": "New Beat Order, HYPR, TECHNO KING",
      "title": "Payphone",
      "timestamp": "1:00:41",
      "timestamp_seconds": 3641
    }
  ],
  "audio_links": [
    "https://www.youtube.com/watch?v=7WxYqlwIYqM"
  ],
  "channel": "Techno Mix",
  "view_count": 611033,
  "mix_id": "technomix_20250222_technomix2025remixesofpopulars_5796529b"
}