{
  "source": "youtube",
  "source_url": "https://www.youtube.com/watch?v=VQNyccFKW7Q",
  "video_id": "VQNyccFKW7Q",
  "scraped_at": "2026-02-09T18:45:17.659873",
  "dj_name": "Techno Mix",
  "mix_title": "TECHNO MIX 2025 \ud83d\udd25 Remixes Of Popular Songs \ud83d\ude0a Techno Bangers #024",
  "duration_seconds": 3796,
  "date": "20250306",
  "description": "\ud83d\udd25 TECHNO MIX 2024 \ud83e\udd18 | Remixes Of Popular Songs \ud83c\udfb6 | Techno Bangers\ud83c\udfa7\n\nGet ready to dive into an electrifying journey of beats, bass, and energy with TECHNO MIX 2024! \ud83d\ude80 This mix is packed with the hottest remixes of your favorite songs and pulsating techno bangers that will keep you grooving all night long. \ud83c\udf89\n\nTimestamp:\n00:00 Yellow Pvnk, TECHNO KING, GopStop - Push Up\n02:05 New Beat Order, lonelysoul, TECHNO KING - Tokyo Drift (feat. ROXANA & Bladez)\n04:10 Wannabebroken, B Martin, TECHNO KING - Sexy Chick\n06:29 Yellow Pvnk, GopStop, TECHNO KING - DADDY DJ\n08:28 OSIREK, TECHNO KING - Pump It Up\n10:41 TECHNO KING - Bloody Mary\n12:27 New Beat Order, Lynhare, TECHNO KING - We Found Love\n14:15 Lawstylez, RAMSES, TECHNO KING - Moonlight Shadow\n16:32 Yellow Pvnk, TECHNO KING, GopStop - Heroes (We Could Be)\n18:40 HITAK, TECHNO KING - All Around The World\n20:46 New Beat Order, HYPR, TECHNO KING - Without Me\n22:53 TECHNO KING - She Doesn't Mind (feat. Shawn O'Donnell)\n24:40 wannabebroken, TECHNO KING - Mystery\n26:53 Heater & Crunch, GopStop, TECHNO KING - I Don't Wanna Wait (feat. Nito-Onna)\n29:09 Onur Ormen, NDR, TECHNO KING - Sweat (feat. KOANS)\n31:50 The Kith, GopStop, TECHNO KING - One More Lie\n33:40 Yellow Pvnk, GopStop,  TECHNO KING - Stereo Love\n35:43 Yellow Pvnk, GopStop, TECHNO KING - Forever Young\n37:52 TRFN, PET3RPUNX, TECHNO KING - Freaks (feat. Siadou)\n39:53 wannabebroken, TECHNO KING - Roses\n42:09 PET3RPUNX, 2Hounds, TECHNO KING - Outside\n44:14 New Beat Order, HYPR, TECHNO KING - Radioactive\n46:30 New Beat Order, HYPR, TECHNO KING feat. KIMERA V - Maniac\n48:59 HITAK, TECHNO KING - Makeba\n51:12 Cour, Snoblack, TECHNO KING  - Winter (from The Four Seasons)\n53:12 Onur Ormen, Reaktive & TECHNO KING - Candy Shop (feat. Flyn Stoned)\n54:58 Sammy & Lesen, Yellow Pvnk, TECHNO KING - See On Me (feat. Shawn o Donnell)\n57:02 New Beat Order, Aaron Richards, TECHNO KING - Numb\n58:52 New Beat Order, Aaron Richards, TECHNO KING - Bring Me To Life\n1:01:19 Ken, TECHNO KING - Infin",
  "genres": [
    "techno mix",
    "remix techno mix",
    "best mix techno",
    "dark techno mix",
    "techno music mix",
    "techno live mix",
    "techno mix 2024",
    "techno remix",
    "techno",
    "hard techno"
  ],
  "tracklist": [
    {
      "position": 1,
      "artist": "Yellow Pvnk, TECHNO KING, GopStop",
      "title": "Push Up",
      "timestamp": "00:00",
      "timestamp_seconds": 0
    },
    {
      "position": 2,
      "artist": "New Beat Order, lonelysoul, TECHNO KING",
      "title": "Tokyo Drift",
      "timestamp": "02:05",
      "timestamp_seconds": 125
    },
    {
      "position": 3,
      "artist": "Wannabebroken, B Martin, TECHNO KING",
      "title": "Sexy Chick",
      "timestamp": "04:10",
      "timestamp_seconds": 250
    },
    {
      "position": 4,
      "artist": "Yellow Pvnk, GopStop, TECHNO KING",
      "title": "DADDY DJ",
      "timestamp": "06:29",
      "timestamp_seconds": 389
    },
    {
      "position": 5,
      "artist": "OSIREK, TECHNO KING",
      "title": "Pump It Up",
      "timestamp": "08:28",
      "timestamp_seconds": 508
    },
    {
      "position": 6,
      "artist": "TECHNO KING",
      "title": "Bloody Mary",
      "timestamp": "10:41",
      "timestamp_seconds": 641
    },
    {
      "position": 7,
      "artist": "New Beat Order, Lynhare, TECHNO KING",
      "title": "We Found Love",
      "timestamp": "12:27",
      "timestamp_seconds": 747
    },
    {
      "position": 8,
      "artist": "Lawstylez, RAMSES, TECHNO KING",
      "title": "Moonlight Shadow",
      "timestamp": "14:15",
      "timestamp_seconds": 855
    },
    {
      "position": 9,
      "artist": "Yellow Pvnk, TECHNO KING, GopStop",
      "title": "Heroes",
      "timestamp": "16:32",
      "timestamp_seconds": 992
    },
    {
      "position": 10,
      "artist": "HITAK, TECHNO KING",
      "title": "All Around The World",
      "timestamp": "18:40",
      "timestamp_seconds": 1120
    },
    {
      "position": 11,
      "artist": "New Beat Order, HYPR, TECHNO KING",
      "title": "Without Me",
      "timestamp": "20:46",
      "timestamp_seconds": 1246
    },
    {
      "position": 12,
      "artist": "TECHNO KING",
      "title": "She Doesn't Mind",
      "timestamp": "22:53",
      "timestamp_seconds": 1373
    },
    {
      "position": 13,
      "artist": "wannabebroken, TECHNO KING",
      "title": "Mystery",
      "timestamp": "24:40",
      "timestamp_seconds": 1480
    },
    {
      "position": 14,
      "artist": "Heater & Crunch, GopStop, TECHNO KING",
      "title": "I Don't Wanna Wait",
      "timestamp": "26:53",
      "timestamp_seconds": 1613
    },
    {
      "position": 15,
      "artist": "Onur Ormen, NDR, TECHNO KING",
      "title": "Sweat",
      "timestamp": "29:09",
      "timestamp_seconds": 1749
    },
    {
      "position": 16,
      "artist": "The Kith, GopStop, TECHNO KING",
      "title": "One More Lie",
      "timestamp": "31:50",
      "timestamp_seconds": 1910
    },
    {
      "position": 17,
      "artist": "Yellow Pvnk, GopStop,  TECHNO KING",
      "title": "Stereo Love",
      "timestamp": "33:40",
      "timestamp_seconds": 2020
    },
    {
      "position": 18,
      "artist": "Yellow Pvnk, GopStop, TECHNO KING",
      "title": "Forever Young",
      "timestamp": "35:43",
      "timestamp_seconds": 2143
    },
    {
      "position": 19,
      "artist": "TRFN, PET3RPUNX, TECHNO KING",
      "title": "Freaks",
      "timestamp": "37:52",
      "timestamp_seconds": 2272
    },
    {
      "position": 20,
      "artist": "wannabebroken, TECHNO KING",
      "title": "Roses",
      "timestamp": "39:53",
      "timestamp_seconds": 2393
    },
    {
      "position": 21,
      "artist": "PET3RPUNX, 2Hounds, TECHNO KING",
      "title": "Outside",
      "timestamp": "42:09",
      "timestamp_seconds": 2529
    },
    {
      "position": 22,
      "artist": "New Beat Order, HYPR, TECHNO KING",
      "title": "Radioactive",
      "timestamp": "44:14",
      "timestamp_seconds": 2654
    },
    {
      "position": 23,
      "artist": "New Beat Order, HYPR, TECHNO KING feat. KIMERA V",
      "title": "Maniac",
      "timestamp": "46:30",
      "timestamp_seconds": 2790
    },
    {
      "position": 24,
      "artist": "HITAK, TECHNO KING",
      "title": "Makeba",
      "timestamp": "48:59",
      "timestamp_seconds": 2939
    },
    {
      "position": 25,
      "artist": "Cour, Snoblack, TECHNO KING",
      "title": "Winter",
      "timestamp": "51:12",
      "timestamp_seconds": 3072
    },
    {
      "position": 26,
      "artist": "Onur Ormen, Reaktive & TECHNO KING",
      "title": "Candy Shop",
      "timestamp": "53:12",
      "timestamp_seconds": 3192
    },
    {
      "position": 27,
      "artist": "Sammy & Lesen, Yellow Pvnk, TECHNO KING",
      "title": "See On Me",
      "timestamp": "54:58",
      "timestamp_seconds": 3298
    },
    {
      "position": 28,
      "artist": "New Beat Order, Aaron Richards, TECHNO KING",
      "title": "Numb",
      "timestamp": "57:02",
      "timestamp_seconds": 3422
    },
    {
      "position": 29,
      "artist": "New Beat Order, Aaron Richards, TECHNO KING",
      "title": "Bring Me To Life",
      "timestamp": "58:52",
      "timestamp_seconds": 3532
    },
    {
      "position": 30,
      "artist": "Ken, TECHNO KING",
      "title": "Infinity",
      "timestamp": "1:01:19",
      "timestamp_seconds": 3679
    }
  ],
  "audio_links": [
    "https://www.youtube.com/watch?v=VQNyccFKW7Q"
  ],
  "channel": "Techno Mix",
  "view_count": 457867,
  "mix_id": "technomix_20250306_technomix2025remixesofpopulars_1196d23d"
}