{
  "source": "youtube",
  "source_url": "https://www.youtube.com/watch?v=PnGi7_Ga0G8",
  "video_id": "PnGi7_Ga0G8",
  "scraped_at": "2026-02-09T18:46:20.967856",
  "dj_name": "Techno Mix",
  "mix_title": "TECHNO MIX 2025 \ud83d\ude0e\u26a1Remixes Of Popular Songs \ud83e\udd1f Techno Bangers #039",
  "duration_seconds": 3806,
  "date": "20250406",
  "description": "\ud83d\udd25 TECHNO MIX 2024 \ud83e\udd18 | Remixes Of Popular Songs \ud83c\udfb6 | Techno Bangers\ud83c\udfa7\n\nGet ready to dive into an electrifying journey of beats, bass, and energy with TECHNO MIX 2024! \ud83d\ude80 This mix is packed with the hottest remixes of your favorite songs and pulsating techno bangers that will keep you grooving all night long. \ud83c\udf89\n\nTimestamp:\n00:00  Wannabebroken, B Martin, TECHNO KING - Sexy Chick\n02:16  Yellow Pvnk, TECHNO KING, GopStop - Push Up\n04:18  HITAK, TECHNO KING - Makeba\n06:22  2Hounds, TECHNO KING - Bad Romance\n08:45  Hyper VIPER, Jazmine, TECHNO KING - Elastic Heart\n11:06  Onur Ormen, NDR, TECHNO KING (feat. KOANS) - Sweat\n13:46  ATHYN, Garonzos & TECHNO KING feat Nito-Onna - 10h35\n15:51  TECHNO KING - Flowers\n18:22  2Hounds, PET3RPUNX, TECHNO KING - I Kissed A Girl\n20:45  New Beat Order, HYPR, TECHNO KING - Radioactive\n22:58  Yellow Pvnk, GopStop, TECHNO KING - DADDY DJ\n24:51  MetaBoy, PET3RPUNX, TECHNO KING - Ayo Technology\n26:43  R3Ly, TECHNO KING - The One For Me\n28:38  Nito-Onna, TECHNO KING - Satisfaction\n30:35  HOMAN, GULIZI, TECHNO KING - Mr. Saxobeat\n32:45  Lawstylez, Mary Lena, TECHNO KING - Bad Boy\n34:57  Ericovich, TECHNO KING - Feel The Rush\n36:45  MetaBoy, DVO, TECHNO KING - I Adore You\n38:42  MetaBoy, Vanessa Campagna, TECHNO KING - Gravity\n40:50  TECHNO KING - Bloody Mary\n42:32  Harddope, Nito-Onna, Rovack - I Like The Way You Kiss Me\n44:44  TECHNO KING - Closer\n46:39  F3DEN, TECHNO KING - Faded Love\n48:48  Booty Leak, HOMINID, TECHNO KING - Kings & Queens\n50:22  Hyper VIPER, TECHNO KING - Mirrors\n\n\nWhat\u2019s inside?\n\ud83c\udfb5 Mind-blowing remixes of popular tracks\n\ud83c\udfb5 High-energy techno beats to set the dance floor on fire\n\ud83c\udfb5 The ultimate vibe for parties, workouts, or just chilling\n\n\u2728 Perfect for:\n\u2714\ufe0f Rave enthusiasts\n\u2714\ufe0f Techno lovers\n\u2714\ufe0f Anyone craving an unforgettable musical escape\n\n\ud83d\udd14 Don\u2019t forget to LIKE, SUBSCRIBE, and SHARE this mix with your friends! Stay tuned for more epic techno bangers and remixes coming your way.\n\n\ud83c\udfa4 Got a favorite track in this mix? Let us know i",
  "genres": [
    "techno mix",
    "remix techno mix",
    "best mix techno",
    "dark techno mix",
    "techno music mix",
    "techno live mix",
    "techno mix 2024",
    "techno remix",
    "techno",
    "hard techno"
  ],
  "tracklist": [
    {
      "position": 1,
      "artist": "Wannabebroken, B Martin, TECHNO KING",
      "title": "Sexy Chick",
      "timestamp": "00:00",
      "timestamp_seconds": 0
    },
    {
      "position": 2,
      "artist": "Yellow Pvnk, TECHNO KING, GopStop",
      "title": "Push Up",
      "timestamp": "02:16",
      "timestamp_seconds": 136
    },
    {
      "position": 3,
      "artist": "HITAK, TECHNO KING",
      "title": "Makeba",
      "timestamp": "04:18",
      "timestamp_seconds": 258
    },
    {
      "position": 4,
      "artist": "2Hounds, TECHNO KING",
      "title": "Bad Romance",
      "timestamp": "06:22",
      "timestamp_seconds": 382
    },
    {
      "position": 5,
      "artist": "Hyper VIPER, Jazmine, TECHNO KING",
      "title": "Elastic Heart",
      "timestamp": "08:45",
      "timestamp_seconds": 525
    },
    {
      "position": 6,
      "artist": "Onur Ormen, NDR, TECHNO KING (feat. KOANS)",
      "title": "Sweat",
      "timestamp": "11:06",
      "timestamp_seconds": 666
    },
    {
      "position": 7,
      "artist": "ATHYN, Garonzos & TECHNO KING feat Nito-Onna",
      "title": "10h35",
      "timestamp": "13:46",
      "timestamp_seconds": 826
    },
    {
      "position": 8,
      "artist": "TECHNO KING",
      "title": "Flowers",
      "timestamp": "15:51",
      "timestamp_seconds": 951
    },
    {
      "position": 9,
      "artist": "2Hounds, PET3RPUNX, TECHNO KING",
      "title": "I Kissed A Girl",
      "timestamp": "18:22",
      "timestamp_seconds": 1102
    },
    {
      "position": 10,
      "artist": "New Beat Order, HYPR, TECHNO KING",
      "title": "Radioactive",
      "timestamp": "20:45",
      "timestamp_seconds": 1245
    },
    {
      "position": 11,
      "artist": "Yellow Pvnk, GopStop, TECHNO KING",
      "title": "DADDY DJ",
      "timestamp": "22:58",
      "timestamp_seconds": 1378
    },
    {
      "position": 12,
      "artist": "MetaBoy, PET3RPUNX, TECHNO KING",
      "title": "Ayo Technology",
      "timestamp": "24:51",
      "timestamp_seconds": 1491
    },
    {
      "position": 13,
      "artist": "R3Ly, TECHNO KING",
      "title": "The One For Me",
      "timestamp": "26:43",
      "timestamp_seconds": 1603
    },
    {
      "position": 14,
      "artist": "Nito-Onna, TECHNO KING",
      "title": "Satisfaction",
      "timestamp": "28:38",
      "timestamp_seconds": 1718
    },
    {
      "position": 15,
      "artist": "HOMAN, GULIZI, TECHNO KING",
      "title": "Mr. Saxobeat",
      "timestamp": "30:35",
      "timestamp_seconds": 1835
    },
    {
      "position": 16,
      "artist": "Lawstylez, Mary Lena, TECHNO KING",
      "title": "Bad Boy",
      "timestamp": "32:45",
      "timestamp_seconds": 1965
    },
    {
      "position": 17,
      "artist": "Ericovich, TECHNO KING",
      "title": "Feel The Rush",
      "timestamp": "34:57",
      "timestamp_seconds": 2097
    },
    {
      "position": 18,
      "artist": "MetaBoy, DVO, TECHNO KING",
      "title": "I Adore You",
      "timestamp": "36:45",
      "timestamp_seconds": 2205
    },
    {
      "position": 19,
      "artist": "MetaBoy, Vanessa Campagna, TECHNO KING",
      "title": "Gravity",
      "timestamp": "38:42",
      "timestamp_seconds": 2322
    },
    {
      "position": 20,
      "artist": "TECHNO KING",
      "title": "Bloody Mary",
      "timestamp": "40:50",
      "timestamp_seconds": 2450
    },
    {
      "position": 21,
      "artist": "Harddope, Nito-Onna, Rovack",
      "title": "I Like The Way You Kiss Me",
      "timestamp": "42:32",
      "timestamp_seconds": 2552
    },
    {
      "position": 22,
      "artist": "TECHNO KING",
      "title": "Closer",
      "timestamp": "44:44",
      "timestamp_seconds": 2684
    },
    {
      "position": 23,
      "artist": "F3DEN, TECHNO KING",
      "title": "Faded Love",
      "timestamp": "46:39",
      "timestamp_seconds": 2799
    },
    {
      "position": 24,
      "artist": "Booty Leak, HOMINID, TECHNO KING",
      "title": "Kings & Queens",
      "timestamp": "48:48",
      "timestamp_seconds": 2928
    },
    {
      "position": 25,
      "artist": "Hyper VIPER, TECHNO KING",
      "title": "Mirrors",
      "timestamp": "50:22",
      "timestamp_seconds": 3022
    }
  ],
  "audio_links": [
    "https://www.youtube.com/watch?v=PnGi7_Ga0G8"
  ],
  "channel": "Techno Mix",
  "view_count": 79745,
  "mix_id": "technomix_20250406_technomix2025remixesofpopulars_8e29c817"
}